[
  {
    "title": "Documenting \"withContactCounts\" for campaign API",
    "url": "https://github.com/mautic/developer-documentation-new/pull/293",
    "repo": "mautic/developer-documentation-new",
    "number": 293,
    "status": "Co-authoring",
    "createdAt": "2026-02-17T09:42:29Z",
    "updatedAt": "2026-04-05T18:12:39Z",
    "labels": [],
    "isDraft": false,
    "body": "Docs for https://github.com/mautic/mautic/pull/15878. This should be rebased to the 7.1 branch once it exists. ",
    "lastActor": "Copilot",
    "isLastActorBot": false,
    "hasFormalReview": true,
    "reviewState": "CHANGES_REQUESTED",
    "lastSubstantiveDate": "2026-03-25T09:59:31.000Z",
    "author": "escopecz"
  },
  {
    "title": "Navigating UI resources",
    "url": "https://github.com/mautic/developer-documentation-new/pull/250",
    "repo": "mautic/developer-documentation-new",
    "number": 250,
    "status": "Co-authoring",
    "createdAt": "2025-06-18T18:26:09Z",
    "updatedAt": "2026-04-21T05:55:56Z",
    "labels": [],
    "isDraft": false,
    "body": "This pull request introduces a new documentation page, \"Navigating and using templates,\" which help developers understand views, platform templates, and organizational standards.\r\n\r\n- where to find\r\n- how to name them\r\n- finding templates",
    "lastActor": "adiati98",
    "isLastActorBot": false,
    "hasFormalReview": true,
    "reviewState": null,
    "lastSubstantiveDate": "2026-04-21T05:55:56.000Z",
    "author": "andersonjeccel"
  },
  {
    "title": "Campaign import export user docs",
    "url": "https://github.com/mautic/user-documentation/pull/361",
    "repo": "mautic/user-documentation",
    "number": 361,
    "status": "Co-authoring",
    "createdAt": "2025-05-09T10:42:30Z",
    "updatedAt": "2026-04-21T08:10:07Z",
    "labels": ["pending-feedback"],
    "isDraft": false,
    "body": "Added descriptions for campaign import and campaign export.\r\n",
    "lastActor": "RCheesley",
    "isLastActorBot": false,
    "hasFormalReview": true,
    "reviewState": "CHANGES_REQUESTED",
    "lastSubstantiveDate": "2026-03-11T11:46:03.000Z",
    "author": "dcjarvis"
  },
  {
    "title": "Add an overview of local.php for mautic 4 documentation",
    "url": "https://github.com/mautic/user-documentation/pull/138",
    "repo": "mautic/user-documentation",
    "number": 138,
    "status": "Co-authoring",
    "createdAt": "2023-02-27T15:34:04Z",
    "updatedAt": "2026-03-19T10:41:32Z",
    "labels": [],
    "isDraft": false,
    "body": "### Add an overview of local.php file based on a mautic 4.4.6 instance\r\n\r\nWe at Leuchtfeuer created this local.php overview as a proposal for the user documentation of mautic 4.\r\nThe impulse to create such an overview for mautic 4 was made by Sven Döring.\r\nSven Döring offered and did already the first proofreading/review. \r\n\r\nThanks a lot for that to Sven Döring.\r\n\r\nSo this PR Version has passed one time proofreading/review, but needs more by the community.\r\n\r\nWe would be glad, if somebody can do the additional review, so that it maybe could be part of the user documentation for mautic 4. \r\n \r\n\r\n",
    "lastActor": "RCheesley",
    "isLastActorBot": false,
    "hasFormalReview": true,
    "reviewState": "APPROVED",
    "lastSubstantiveDate": "2026-03-19T10:41:32.000Z",
    "author": "beetofly"
  }
]
